geneplore_bare_api/__init__.py
geneplore_bare_api/api_sync.py
geneplore_bare_api-3.6.2.dist-info/LICENSE
geneplore_bare_api-3.6.2.dist-info/METADATA
geneplore_bare_api-3.6.2.dist-info/WHEEL
geneplore_bare_api-3.6.2.dist-info/top_level.txt
geneplore_bare_api-3.6.2.dist-info/RECORD
