Metadata-Version: 2.1
Name: geneplore_bare_api
Version: 3.6.2
Summary: The bare API for Geneplore AI's API. Don't use this library directly, use geneplore_api instead after signing up at https://geneplore.com .
Author-email: thegamebegins25 <will@geneplore.com>
Project-URL: Homepage, https://github.com/GeneploreAI/geneplore-api
Project-URL: Bug Tracker, https://github.com/GeneploreAI/geneplore-api/issues
Classifier: Programming Language :: Python :: 3
Classifier: License :: Other/Proprietary License
Classifier: Operating System :: OS Independent
Classifier: Development Status :: 3 - Alpha
Requires-Python: >=3.7
License-File: LICENSE
Requires-Dist: requests
Requires-Dist: pandas
Requires-Dist: google-api-python-client
Requires-Dist: google-api-core
Requires-Dist: python-dotenv
Requires-Dist: boto3
